src/__init__.py
src/context.py
src/file_system.py
src/get_editable_text.py
src/get_editor_command.py
src/goodies.py
src/logger.py
src/parse_edited_text.py
src/paths_to_inodes_paths.py
src/printer.py
src/renamings.py
src/secure_clauses.py
src/suprenam.py
src/user_errors.py
src/user_types.py
suprenam-0.9.9b15.dist-info/LICENSE
suprenam-0.9.9b15.dist-info/METADATA
suprenam-0.9.9b15.dist-info/WHEEL
suprenam-0.9.9b15.dist-info/entry_points.txt
suprenam-0.9.9b15.dist-info/top_level.txt
suprenam-0.9.9b15.dist-info/RECORD
