Metadata-Version: 2.1
Name: suprenam
Version: 0.9.9b15
Summary: Easily rename files and folders via your favorite text editor.
Home-page: https://github.com/poponealex/suprenam
Author: Aristide Grange & Alexandre Perlmutter
Author-email: alexandre.perlmutter@gmail.com
License: UNKNOWN
Platform: UNKNOWN
Classifier: Programming Language :: Python :: 3
Classifier: License :: OSI Approved :: MIT License
Classifier: Operating System :: OS Independent
Requires-Python: >=3.6
License-File: LICENSE
Requires-Dist: pathvalidate (==2.5.0)
